ivf/__init__.py
ivf/config/__init__.py
ivf/config/config.py
ivf/files/__init__.py
ivf/files/files.py
invalidfire_utils-2020.10.9.1.dist-info/LICENSE
invalidfire_utils-2020.10.9.1.dist-info/METADATA
invalidfire_utils-2020.10.9.1.dist-info/WHEEL
invalidfire_utils-2020.10.9.1.dist-info/top_level.txt
invalidfire_utils-2020.10.9.1.dist-info/RECORD
