Metadata-Version: 2.1
Name: invalidfire-utils
Version: 2020.10.9.1
Summary: Various Utilities for my projects.
Home-page: https://github.com/InValidFire/invalidfire-utils
Author: InValidFire
Author-email: UNKNOWN
License: The Unlicense
Platform: UNKNOWN
